pytest_relay_run/__init__.py
pytest_relay_run/main.py
pytest_relay_run/py.typed
pytest_relay_run/api/__init__.py
pytest_relay_run/api/app.py
pytest_relay_run/api/job.py
pytest_relay_run/api/model.py
pytest_relay_run/ws/__init__.py
pytest_relay_run/ws/app.py
pytest_relay_run-0.0.1.dist-info/METADATA
pytest_relay_run-0.0.1.dist-info/WHEEL
pytest_relay_run-0.0.1.dist-info/entry_points.txt
pytest_relay_run-0.0.1.dist-info/licenses/COPYING
pytest_relay_run-0.0.1.dist-info/RECORD
